koheron_tcp_client/__init__.py
koheron_tcp_client/kclient.py
koheron_tcp_client-0.9.0.dist-info/DESCRIPTION.rst
koheron_tcp_client-0.9.0.dist-info/METADATA
koheron_tcp_client-0.9.0.dist-info/RECORD
koheron_tcp_client-0.9.0.dist-info/WHEEL
koheron_tcp_client-0.9.0.dist-info/entry_points.txt
koheron_tcp_client-0.9.0.dist-info/metadata.json
koheron_tcp_client-0.9.0.dist-info/top_level.txt
